snowflake_pandas/__init__.py
snowflake_pandas/main.py
snowflake_pandas-0.1.2.dist-info/LICENSE.txt
snowflake_pandas-0.1.2.dist-info/METADATA
snowflake_pandas-0.1.2.dist-info/WHEEL
snowflake_pandas-0.1.2.dist-info/top_level.txt
snowflake_pandas-0.1.2.dist-info/RECORD
