Metadata-Version: 2.1
Name: snowflake_pandas
Version: 0.1.2
Summary: Snowflake Connector Package for Python and Pandas by hiteshlabs[dot]com.
Home-page: https://github.com/hitesh-c/snowflake-pandas
Author: Hitesh
License: MIT
Classifier: Programming Language :: Python :: 3
Classifier: License :: OSI Approved :: MIT License
Classifier: Operating System :: OS Independent
Requires-Python: >=3.8
License-File: LICENSE.txt
Requires-Dist: snowflake-connector-python[pandas]
Requires-Dist: pandas
